setup.py
skylark.py
skylark.egg-info/PKG-INFO
skylark.egg-info/SOURCES.txt
skylark.egg-info/dependency_links.txt
skylark.egg-info/top_level.txt