Metadata-Version: 1.1
Name: skylark
Version: 0.7.1
Summary: A nice micro orm for python, mysql only.
Home-page: https://github.com/hit9/skylark
Author: hit9
Author-email: nz2324@126.com
License: BSD
Keywords: ORM MySQL Python tiny micro database
Platform: UNKNOWN
Classifier: Development Status :: 4 - Beta
Classifier: Environment :: Web Environment
Classifier: Intended Audience :: Developers
Classifier: License :: OSI Approved :: BSD License
Classifier: Operating System :: OS Independent
Classifier: Programming Language :: Python
Classifier: Programming Language :: Python :: 3
Classifier: Topic :: Database
Classifier: Topic :: Software Development :: Libraries :: Python Modules
